odoo10_addon_l10n_br_sale-10.0.1.0.0.99.dev55-py3.8-nspkg.pth
odoo/addons/l10n_br_sale/README.rst
odoo/addons/l10n_br_sale/__init__.py
odoo/addons/l10n_br_sale/__manifest__.py
odoo/addons/l10n_br_sale/data/l10n_br_sale_data.xml
odoo/addons/l10n_br_sale/demo/l10n_br_sale_demo.xml
odoo/addons/l10n_br_sale/i18n/l10n_br_sale.pot
odoo/addons/l10n_br_sale/models/__init__.py
odoo/addons/l10n_br_sale/models/res_company.py
odoo/addons/l10n_br_sale/models/res_config.py
odoo/addons/l10n_br_sale/models/sale.py
odoo/addons/l10n_br_sale/models/sale_line.py
odoo/addons/l10n_br_sale/readme/CONFIGURE.rst
odoo/addons/l10n_br_sale/readme/CONTRIBUTORS.rst
odoo/addons/l10n_br_sale/readme/CREDITS.rst
odoo/addons/l10n_br_sale/readme/DESCRIPTION.rst
odoo/addons/l10n_br_sale/readme/HISTORY.rst
odoo/addons/l10n_br_sale/readme/INSTALL.rst
odoo/addons/l10n_br_sale/readme/ROADMAP.rst
odoo/addons/l10n_br_sale/readme/USAGE.rst
odoo/addons/l10n_br_sale/report/__init__.py
odoo/addons/l10n_br_sale/report/sale_report.py
odoo/addons/l10n_br_sale/report/sale_report_view.xml
odoo/addons/l10n_br_sale/security/ir.model.access.csv
odoo/addons/l10n_br_sale/security/l10n_br_sale_security.xml
odoo/addons/l10n_br_sale/static/description/icon.png
odoo/addons/l10n_br_sale/static/description/index.html
odoo/addons/l10n_br_sale/tests/__init__.py
odoo/addons/l10n_br_sale/tests/test_l10n_br_sale.py
odoo/addons/l10n_br_sale/views/res_company_view.xml
odoo/addons/l10n_br_sale/views/res_config_view.xml
odoo/addons/l10n_br_sale/views/sale_view.xml
odoo10_addon_l10n_br_sale-10.0.1.0.0.99.dev55.dist-info/METADATA
odoo10_addon_l10n_br_sale-10.0.1.0.0.99.dev55.dist-info/WHEEL
odoo10_addon_l10n_br_sale-10.0.1.0.0.99.dev55.dist-info/namespace_packages.txt
odoo10_addon_l10n_br_sale-10.0.1.0.0.99.dev55.dist-info/top_level.txt
odoo10_addon_l10n_br_sale-10.0.1.0.0.99.dev55.dist-info/RECORD
