Metadata-Version: 2.1
Name: odoo10-addon-l10n-br-sale
Version: 10.0.1.0.0.99.dev55
Summary: Brazilian Localization Sale
Home-page: http://odoo-brasil.org
Author: Akretion, Odoo Community Association (OCA)
Author-email: support@odoo-community.org
License: AGPL-3
Platform: UNKNOWN
Classifier: Programming Language :: Python
Classifier: Framework :: Odoo
Classifier: Framework :: Odoo :: 10.0
Classifier: License :: OSI Approved :: GNU Affero General Public License v3
Classifier: Development Status :: 5 - Production/Stable
Requires-Python: ~=2.7
Requires-Dist: odoo10-addon-account-fiscal-position-rule-sale
Requires-Dist: odoo10-addon-l10n-br-account
Requires-Dist: odoo <10.1dev,>=10.0
